hashint.py
hashint-1.0.dist-info/METADATA
hashint-1.0.dist-info/WHEEL
hashint-1.0.dist-info/top_level.txt
hashint-1.0.dist-info/RECORD
