Metadata-Version: 2.1
Name: hashint
Version: 1.0
Summary: Easily hash string
Author: lolo859
Keywords: hash,hashint,hsht
Classifier: Natural Language :: French
Classifier: Topic :: Security :: Cryptography
Classifier: Topic :: Software Development :: Code Generators
Requires-Dist: docutils >=0.3
Requires-Dist: pillow
